kube_transform/__init__.py
kube_transform/fsutil.py
kube_transform/spec.py
kube_transform/controller/__init__.py
kube_transform/controller/controller.py
kube_transform/controller/k8s.py
kube_transform/controller/pipeline_manager.py
kube_transform/controller/submit.py
kube_transform-0.2.1.dist-info/licenses/LICENSE
kube_transform-0.2.1.dist-info/METADATA
kube_transform-0.2.1.dist-info/WHEEL
kube_transform-0.2.1.dist-info/top_level.txt
kube_transform-0.2.1.dist-info/RECORD
