Metadata-Version: 2.4
Name: kube-transform
Version: 0.2.1
Summary: A lightweight open-source framework for writing and deploying distributed data transformations on Kubernetes.
Author-email: Devin Toth <devin.r.toth@gmail.com>
Project-URL: Homepage, https://github.com/dtoth/kube-transform
Requires-Python: >=3.11
License-File: LICENSE
Requires-Dist: kubernetes==32.0.1
Requires-Dist: boto3==1.34.91
Requires-Dist: fsspec==2025.3.0
Requires-Dist: s3fs==2025.3.0
Requires-Dist: pydantic==2.11.1
Dynamic: license-file
